{
    "account_status": [],
    "allow_message": true,
    "answer_count": 140,
    "articles_count": 2,
    "available_medals_count": 0,
    "avatar_hue": "",
    "avatar_url": "https://pic1.zhimg.com/9c586eb92cc879df61d8b8328165204f_l.jpg?source=32738c0c",
    "avatar_url_template": "https://pica.zhimg.com/9c586eb92cc879df61d8b8328165204f.jpg?source=32738c0c",
    "badge": [],
    "badge_v2": {
        "detail_badges": [],
        "icon": "",
        "merged_badges": [],
        "night_icon": "",
        "title": ""
    },
    "business": {
        "avatar_url": "https://pic1.zhimg.com/v2-c1ea3804dc369dbfad3de0c405c0a3d2_l.jpg?source=32738c0c",
        "id": "19550517",
        "name": "互联网",
        "type": "topic",
        "url": "https://www.zhihu.com/api/v4/topics/19550517"
    },
    "columns_count": 1,
    "commercial_question_count": 0,
    "cover_url": "https://pica.zhimg.com/v2-409c0e6ac1fd6fd6d82ab34e97a27dd5_r.jpg?source=32738c0c",
    "description": "",
    "educations": [],
    "employments": [],
    "favorite_count": 3,
    "favorited_count": 6626,
    "follower_count": 10064,
    "following_columns_count": 79,
    "following_count": 1606,
    "following_favlists_count": 20,
    "following_question_count": 1943,
    "following_topic_count": 58,
    "gender": 0,
    "has_applying_column": false,
    "headline": "做自己喜欢的事，让喜欢的事有价值~",
    "headline_render": "做自己喜欢的事，让喜欢的事有价值~",
    "hosted_live_count": 0,
    "id": "46a588b2d664291f7fb5fec44bc60f71",
    "included_answers_count": 1,
    "included_articles_count": 0,
    "included_text": "编辑推荐",
    "ip_info": "IP 属地上海",
    "is_active": 1,
    "is_advertiser": false,
    "is_bind_sina": false,
    "is_blocked": false,
    "is_blocking": false,
    "is_followed": false,
    "is_following": false,
    "is_force_renamed": false,
    "is_org": false,
    "is_privacy_protected": true,
    "is_realname": true,
    "locations": [
        {
            "avatar_url": "https://picx.zhimg.com/v2-c4ea2cf2874e37de62190e781529b3dd_l.jpg?source=32738c0c",
            "id": "19550818",
            "name": "上海",
            "type": "topic",
            "url": "https://www.zhihu.com/api/v4/topics/19550818"
        }
    ],
    "logs_count": 101,
    "message_thread_token": "6196724000",
    "mutual_followees_count": 0,
    "name": "娄萌萌",
    "participated_live_count": 4,
    "pins_count": 20,
    "question_count": 21,
    "thank_from_count": 0,
    "thank_to_count": 0,
    "thanked_count": 1816,
    "type": "people",
    "url": "https://www.zhihu.com/api/v4/people/mm.lou",
    "url_token": "mm.lou",
    "use_default_avatar": false,
    "user_type": "people",
    "vip_info": {
        "entrance_v2": null,
        "is_vip": false,
        "rename_await_days": 0,
        "rename_days": "0",
        "rename_frequency": 0,
        "vip_type": 0
    },
    "vote_from_count": 0,
    "vote_to_count": 0,
    "voteup_count": 5640
}